{"develop_doc_develop.md":"BxaBP1kS","develop_doc_develop_format.md":"CmQexQj-","develop_doc_develop_guide.md":"Be3A8cGz","develop_doc_docs.md":"9V9ujfyy","develop_doc_env.md":"CcRnpFak","develop_doc_log.md":"Cc2jA_YB","develop_doc_script_activity.md":"CO9d-Ypp","develop_doc_script_baas_thread.md":"BrvzKT7G","develop_doc_script_config.md":"D8S-i14B","develop_doc_script_configset.md":"DBUTejIC","develop_doc_script_connection.md":"PAmkajn8","develop_doc_script_control.md":"D7hndFds","develop_doc_script_device_operation.md":"D7DHXqRc","develop_doc_script_game_feature.md":"C7xQwRJp","develop_doc_script_image_compare.md":"Mq0Fvrtu","develop_doc_script_image_resource.md":"6szniX09","develop_doc_script_main.md":"VHjmUzBw","develop_doc_script_nemu.md":"C-ixLAJm","develop_doc_script_ocr.md":"DXVBSmPA","develop_doc_script_screenshot.md":"Cps1D_vR","i18n.md":"DLsuIVle","index.md":"C0ZNYR7A","markdown-examples.md":"C-AW0TIA","thanks.md":"aANEdkVU","usage_doc_about.md":"Br9xhETm","usage_doc_activity.md":"oOAkEzUN","usage_doc_api-examples.md":"Ckigyi0X","usage_doc_cli.md":"Bf_W4BAt","usage_doc_config.md":"C7ljwZal","usage_doc_destroyer.md":"Bthcx6PE","usage_doc_downloads.md":"K3SH8I1L","usage_doc_faq.md":"CqNxOSfG","usage_doc_features.md":"Cyu1ZHE8","usage_doc_guide.md":"DmOfmJ8Z","usage_doc_install_choose_platform.md":"CINngrHZ","usage_doc_install_setup_config.md":"CqzONqVP","usage_doc_install_windows.md":"De6AaUNU","usage_doc_qq_group_regulation.md":"CTso8Dsu","usage_doc_report.md":"C61kTlG2","usage_doc_uninstall.md":"CwnhgW_G","usage_doc_update.md":"CRx5QcSH"}
